tinyshakespeareloader/__init__.py
tinyshakespeareloader/hamlet.py
tinyshakespeareloader-1.8.0.dist-info/METADATA
tinyshakespeareloader-1.8.0.dist-info/WHEEL
tinyshakespeareloader-1.8.0.dist-info/RECORD
