Metadata-Version: 2.1
Name: tinyshakespeareloader
Version: 1.8.0
Summary: 
License: MIT
Author: Artur A. Galstyan
Author-email: galstyan.artu@gmail.com
Requires-Python: >=3.10,<4.0
Classifier: License :: OSI Approved :: MIT License
Classifier: Programming Language :: Python :: 3
Classifier: Programming Language :: Python :: 3.10
Classifier: Programming Language :: Python :: 3.11
Requires-Dist: jaxtyping (>=0.2.22,<0.3.0)
Requires-Dist: torch (>=2.1.0,<3.0.0)
